Metadata-Version: 2.1
Name: AWSGeneral
Version: 0.1
Summary: AWS pen testing tool
Author: Bentalem
Author-email: your.email@example.com
